strawhat/__init__.py
strawhat/api.py
strawhat/aws.py
strawhat/files.py
strawhat/logger.py
strawhat/misc.py
strawhat-0.2.0.dist-info/LICENSE
strawhat-0.2.0.dist-info/METADATA
strawhat-0.2.0.dist-info/WHEEL
strawhat-0.2.0.dist-info/top_level.txt
strawhat-0.2.0.dist-info/RECORD
