Metadata-Version: 2.1
Name: strawhat
Version: 0.2.0
Summary: Wrapper module for aws boto3
Author-email: Mridul Ahluwalia <ahluwaliamridul@gmail.com>
License: MIT License        
Keywords: strawhat,aws,boto3
Classifier: License :: OSI Approved :: MIT License
Classifier: Programming Language :: Python
Classifier: Programming Language :: Python :: 3
Requires-Python: >=3.9
License-File: LICENSE
Requires-Dist: jmespath
Requires-Dist: six
Requires-Dist: python-dateutil
Requires-Dist: urllib3
Requires-Dist: botocore
Requires-Dist: s3transfer
Requires-Dist: boto3
